gjf/__init__.py
gjf/__main__.py
gjf/cli.py
gjf/geojson_fixer.py
gjf-0.1.2.dist-info/LICENSE
gjf-0.1.2.dist-info/METADATA
gjf-0.1.2.dist-info/WHEEL
gjf-0.1.2.dist-info/entry_points.txt
gjf-0.1.2.dist-info/top_level.txt
gjf-0.1.2.dist-info/RECORD
