Metadata-Version: 2.1
Name: gjf
Version: 0.1.2
Summary: A tool to fix invalid GeoJSON objects
Home-page: https://github.com/yazeed44/gjf
Author: Yazeed Almuqwishi
Author-email: yazeed.almuqwishi@gmail.com
License: UNKNOWN
Project-URL: Bug Tracker, https://github.com/yazeed44/gjf/issues
Keywords: geojson,fix,python,cli,validation
Platform: UNKNOWN
Classifier: Programming Language :: Python :: 3
Classifier: License :: OSI Approved :: MIT License
Classifier: Operating System :: OS Independent
License-File: LICENSE
Requires-Dist: geojson
Requires-Dist: geojson-rewind
Requires-Dist: click
Requires-Dist: Shapely (>=1.8a1)
